ml/__init__.py
ml/algorithms.py
nunnpyy/__init__.py
nunnpyy/algorithms.py
nunnpyy-1.0.0.dist-info/METADATA
nunnpyy-1.0.0.dist-info/WHEEL
nunnpyy-1.0.0.dist-info/top_level.txt
nunnpyy-1.0.0.dist-info/RECORD
